wavemap_paper/__init__.py
wavemap_paper/helper_functions.py
wavemap_paper-0.1.12.dist-info/LICENSE
wavemap_paper-0.1.12.dist-info/WHEEL
wavemap_paper-0.1.12.dist-info/METADATA
wavemap_paper-0.1.12.dist-info/RECORD
