Metadata-Version: 2.1
Name: wavemap-paper
Version: 0.1.12
Summary: 
Author: Eric Kenji Lee
Author-email: erickenjilee@gmail.com
Requires-Python: >=3.8,<3.9
Classifier: Programming Language :: Python :: 3
Classifier: Programming Language :: Python :: 3.8
Requires-Dist: bokeh (>=3.0.3,<4.0.0)
Requires-Dist: cylouvain (>=0.2.2,<0.3.0)
Requires-Dist: ipykernel (>=6.19.2,<7.0.0)
Requires-Dist: jupyterlab (>=3.5.1,<4.0.0)
Requires-Dist: matplotlib (>=3.6.2,<4.0.0)
Requires-Dist: networkx (>=2.8.8,<3.0.0)
Requires-Dist: scikit-learn (>=1.2.0,<2.0.0)
Requires-Dist: shap (>=0.41.0,<0.42.0)
Requires-Dist: umap-learn (>=0.5.3,<0.6.0)
Requires-Dist: xgboost (>=1.7.2,<2.0.0)
